VarOperHelper/__init__.py
VarOperHelper/datamodel.py
VarOperHelper/operHelper.py
hc_varoperhelper-1.0.2.dist-info/METADATA
hc_varoperhelper-1.0.2.dist-info/RECORD
hc_varoperhelper-1.0.2.dist-info/WHEEL
hc_varoperhelper-1.0.2.dist-info/top_level.txt
