Metadata-Version: 2.1
Name: hc-varoperhelper
Version: 1.0.2
Summary: hc-varoperhelper
Home-page: http://www.haocang.com
Author: HC
Author-email: jiyungen@haocang.com
License: MIT
Platform: UNKNOWN
Classifier: Programming Language :: Python :: 3
Classifier: License :: OSI Approved :: MIT License
Classifier: Operating System :: OS Independent
Requires-Python: ~=3.7
Requires-Dist: requests
